snippettoni/__init__.py
snippettoni/injector.py
snippettoni/main.py
snippettoni/renderer.py
snippettoni/templates/curl.j2
snippettoni/templates/python.j2
snippettoni-0.1.2.dist-info/METADATA
snippettoni-0.1.2.dist-info/WHEEL
snippettoni-0.1.2.dist-info/entry_points.txt
snippettoni-0.1.2.dist-info/licenses/LICENSE.txt
snippettoni-0.1.2.dist-info/RECORD
