Metadata-Version: 2.4
Name: snippettoni
Version: 0.1.2
Summary: Generate the `x-codeSamples` extension for OpenAPI specifications
Project-URL: Homepage, https://github.com/ffaraone/snippettoni
Project-URL: Documentation, https://github.com/ffaraone/snippettoni#readme
Project-URL: Repository, https://github.com/ffaraone/snippettoni.git
Project-URL: Issues, https://github.com/ffaraone/snippettoni/issues
Author: Francesco Faraone
License:                                  Apache License
License-File: LICENSE.txt
Keywords: codeSamples,openapi,redoc,snippets
Classifier: Development Status :: 4 - Beta
Classifier: Intended Audience :: Developers
Classifier: License :: OSI Approved :: Apache Software License
Classifier: Programming Language :: Python :: 3
Classifier: Programming Language :: Python :: 3.12
Classifier: Topic :: Software Development :: Libraries :: Python Modules
Requires-Python: <4,>=3.12
Requires-Dist: jinja2>=3.1.6
Requires-Dist: openapi-spec-validator>=0.7.2
Requires-Dist: prance>=25.4.8.0
Requires-Dist: pyyaml>=6.0.2
Requires-Dist: typer>=0.16.0
